{
  "global": {
    "Color": {
      "Base": {
        "White": {
          "value": "#ffffff",
          "type": "color"
        },
        "Black": {
          "value": "#000000",
          "type": "color"
        },
        "transparent": {
          "value": "#ffffff00",
          "type": "color"
        }
      },
      "Background": {
        "Weak": {
          "value": "{Color.Base.White}",
          "type": "color"
        },
        "Medium": {
          "value": "{Color.Neutral.25}",
          "type": "color"
        },
        "Strong": {
          "value": "{Color.Neutral.50}",
          "type": "color"
        },
        "Hover": {
          "value": "{Color.Neutral.25}",
          "type": "color"
        },
        "Active": {
          "value": "{Color.Neutral.50}",
          "type": "color"
        }
      },
      "Text": {
        "Default": {
          "value": "{Color.Neutral.900}",
          "type": "color",
          "description": "#212429"
        },
        "Foreground": {
          "value": "{Color.Base.White}",
          "type": "color"
        },
        "Weak": {
          "value": "{Color.Neutral.500}",
          "type": "color"
        },
        "Weak-Hover": {
          "value": "{Color.Neutral.900}",
          "type": "color"
        },
        "Disabled": {
          "value": "{Color.Neutral.300}",
          "type": "color",
          "description": "#A7ADB9"
        }
      },
      "Icon": {
        "Default": {
          "value": "{Color.Neutral.500}",
          "type": "color"
        },
        "Foreground": {
          "value": "{Color.Base.White}",
          "type": "color"
        },
        "Hover": {
          "value": "{Color.Neutral.900}",
          "type": "color"
        },
        "Disabled": {
          "value": "{Color.Neutral.300}",
          "type": "color"
        }
      },
      "Border": {
        "Default": {
          "value": "#e2e4e8",
          "type": "color"
        },
        "Inverse": {
          "value": "#ffffff",
          "type": "color"
        },
        "Strong": {
          "value": "#c5c9d0",
          "type": "color",
          "description": "#C5C9D0"
        },
        "Hover": {
          "value": "#a7adb9",
          "type": "color"
        },
        "Active": {
          "value": "#6d778a",
          "type": "color",
          "description": "#5366D4"
        },
        "Weak": {
          "value": "#ffffff",
          "type": "color"
        }
      },
      "Primary": {
        "25": {
          "value": "#f9f9fe",
          "type": "color",
          "description": "#F9F9FE"
        },
        "50": {
          "value": "#e9ecfa",
          "type": "color",
          "description": "#E9ECFA"
        },
        "100": {
          "value": "#d9ddf6",
          "type": "color",
          "description": "#D9DDF6"
        },
        "200": {
          "value": "#c8cef1",
          "type": "color",
          "description": "#C8CEF1"
        },
        "300": {
          "value": "#b7bfed",
          "type": "color",
          "description": "#B7BFED"
        },
        "400": {
          "value": "#96a1e5",
          "type": "color",
          "description": "#96A2E5"
        },
        "500": {
          "value": "#5366d4",
          "type": "color",
          "description": "#5366D4"
        },
        "600": {
          "value": "#4657b7",
          "type": "color",
          "description": "#4657B7"
        },
        "700": {
          "value": "#39479b",
          "type": "color",
          "description": "#39479B"
        },
        "800": {
          "value": "#2b387e",
          "type": "color",
          "description": "#2B387E"
        },
        "900": {
          "value": "#253070",
          "type": "color",
          "description": "#253070"
        }
      },
      "Neutral": {
        "25": {
          "value": "#f5f7fa",
          "type": "color",
          "description": "#F5F7FA\n"
        },
        "50": {
          "value": "#f0f1f3",
          "type": "color",
          "description": "#F0F1F3"
        },
        "100": {
          "value": "#e2e4e8",
          "type": "color",
          "description": "#E2E4E8"
        },
        "200": {
          "value": "#d3d6dc",
          "type": "color",
          "description": "#D3D6DC"
        },
        "300": {
          "value": "#c5c9d0",
          "type": "color",
          "description": "#C5C9D0"
        },
        "400": {
          "value": "#a7adb9",
          "type": "color",
          "description": "#A7ADB9"
        },
        "500": {
          "value": "#6d778a",
          "type": "color",
          "description": "#6D778A"
        },
        "600": {
          "value": "#575f6e",
          "type": "color",
          "description": "#575F6E"
        },
        "700": {
          "value": "#414753",
          "type": "color",
          "description": "#414753"
        },
        "800": {
          "value": "#2c3037",
          "type": "color",
          "description": "#2C3037"
        },
        "900": {
          "value": "#212429",
          "type": "color",
          "description": "#212429"
        }
      },
      "Info": {
        "25": {
          "value": "#fafcff",
          "type": "color",
          "description": "FAFCFF"
        },
        "50": {
          "value": "#eaf1fc",
          "type": "color",
          "description": "EAF1FC"
        },
        "100": {
          "value": "#d5e3fa",
          "type": "color",
          "description": "D4E2FA"
        },
        "200": {
          "value": "#bfd5f7",
          "type": "color",
          "description": "BFD5F7"
        },
        "300": {
          "value": "#aac7f5",
          "type": "color",
          "description": "AAC6F5"
        },
        "400": {
          "value": "#80aaf0",
          "type": "color",
          "description": "80AAF0"
        },
        "500": {
          "value": "#2b72e6",
          "type": "color",
          "description": "2B72E6"
        },
        "600": {
          "value": "#225bb8",
          "type": "color",
          "description": "225BB8"
        },
        "700": {
          "value": "#1a448a",
          "type": "color",
          "description": "1A448A"
        },
        "800": {
          "value": "#112e5c",
          "type": "color",
          "description": "112E5C"
        },
        "900": {
          "value": "#0d2245",
          "type": "color",
          "description": "0D2245"
        }
      },
      "Success": {
        "25": {
          "value": "#f7fcf9",
          "type": "color",
          "description": "F7FCF9"
        },
        "50": {
          "value": "#ddf2e6",
          "type": "color",
          "description": "DDF2E6"
        },
        "100": {
          "value": "#c8e8d5",
          "type": "color",
          "description": "C8E8D5"
        },
        "200": {
          "value": "#b3ddc5",
          "type": "color",
          "description": "B3DDC5"
        },
        "300": {
          "value": "#9ed3b5",
          "type": "color",
          "description": "9ED3B5"
        },
        "400": {
          "value": "#75bf94",
          "type": "color",
          "description": "75BF94"
        },
        "500": {
          "value": "#138845",
          "type": "color",
          "description": "138845"
        },
        "600": {
          "value": "#1a7842",
          "type": "color",
          "description": "1A7842"
        },
        "700": {
          "value": "#145a32",
          "type": "color",
          "description": "135A31"
        },
        "800": {
          "value": "#0d3c21",
          "type": "color",
          "description": "0D3C21"
        },
        "900": {
          "value": "#0a2d19",
          "type": "color",
          "description": "092D18"
        }
      },
      "Warning": {
        "25": {
          "value": "#fffcf7",
          "type": "color",
          "description": "FFFCF7"
        },
        "50": {
          "value": "#fef5e7",
          "type": "color",
          "description": "FDF0DA"
        },
        "100": {
          "value": "#fdecce",
          "type": "color",
          "description": "FCE8C3"
        },
        "200": {
          "value": "#fce2b6",
          "type": "color",
          "description": "FBDEAC"
        },
        "300": {
          "value": "#fbd89d",
          "type": "color",
          "description": "FAD595"
        },
        "400": {
          "value": "#f9c367",
          "type": "color",
          "description": "F9C367"
        },
        "500": {
          "value": "#f59e0b",
          "type": "color",
          "description": "F59E0B"
        },
        "600": {
          "value": "#a46a07",
          "type": "color",
          "description": "AC7312"
        },
        "700": {
          "value": "#935f07",
          "type": "color",
          "description": "995506"
        },
        "800": {
          "value": "#623f04",
          "type": "color",
          "description": "6C4505"
        },
        "900": {
          "value": "#492f03",
          "type": "color",
          "description": "543604"
        }
      },
      "Error": {
        "25": {
          "value": "#fffafa",
          "type": "color",
          "description": "FFF9F9"
        },
        "50": {
          "value": "#f9e5e5",
          "type": "color",
          "description": "F9E5E5"
        },
        "100": {
          "value": "#f5d2d2",
          "type": "color",
          "description": "F5D2D2"
        },
        "200": {
          "value": "#f1c0c0",
          "type": "color",
          "description": "F1C0C0"
        },
        "300": {
          "value": "#edaeae",
          "type": "color",
          "description": "EDAEAE"
        },
        "400": {
          "value": "#e48989",
          "type": "color",
          "description": "E48989"
        },
        "500": {
          "value": "#d44040",
          "type": "color",
          "description": "D44040"
        },
        "600": {
          "value": "#b23535",
          "type": "color",
          "description": "B23535"
        },
        "700": {
          "value": "#902a2a",
          "type": "color",
          "description": "902A2A"
        },
        "800": {
          "value": "#6e1f1f",
          "type": "color",
          "description": "6E1F1F"
        },
        "900": {
          "value": "#5d1919",
          "type": "color",
          "description": "5D1919"
        }
      },
      "Gray": {
        "25": {
          "value": "#fcfcfc",
          "type": "color",
          "description": "FCFCFC"
        },
        "50": {
          "value": "#f1f1f1",
          "type": "color",
          "description": "F1F1F1"
        },
        "100": {
          "value": "#e3e3e3",
          "type": "color",
          "description": "E3E3E3"
        },
        "200": {
          "value": "#d5d5d5",
          "type": "color",
          "description": "D5D5D5"
        },
        "300": {
          "value": "#c7c7c7",
          "type": "color",
          "description": "C7C7C7"
        },
        "400": {
          "value": "#ababab",
          "type": "color",
          "description": "ABABAB"
        },
        "500": {
          "value": "#737373",
          "type": "color",
          "description": "737373"
        },
        "600": {
          "value": "#5c5c5c",
          "type": "color",
          "description": "5C5C5C"
        },
        "700": {
          "value": "#454545",
          "type": "color",
          "description": "454545"
        },
        "800": {
          "value": "#2e2e2e",
          "type": "color",
          "description": "2E2E2E"
        },
        "900": {
          "value": "#222222",
          "type": "color",
          "description": "222222"
        }
      },
      "Orange": {
        "25": {
          "value": "#fef9f6",
          "type": "color",
          "description": "FEF9F6"
        },
        "50": {
          "value": "#fde3d2",
          "type": "color",
          "description": "FDE3D2"
        },
        "100": {
          "value": "#fdd7bd",
          "type": "color",
          "description": "FDD7BD"
        },
        "200": {
          "value": "#fccaa8",
          "type": "color",
          "description": "FCCAA8"
        },
        "300": {
          "value": "#fcbe93",
          "type": "color",
          "description": "FCBE93"
        },
        "400": {
          "value": "#fba56a",
          "type": "color",
          "description": "FBA56A"
        },
        "500": {
          "value": "#f97316",
          "type": "color",
          "description": "F97316"
        },
        "600": {
          "value": "#c55405",
          "type": "color",
          "description": "C55405"
        },
        "700": {
          "value": "#ab4f0e",
          "type": "color",
          "description": "AB4E0D"
        },
        "800": {
          "value": "#843c09",
          "type": "color",
          "description": "843C09"
        },
        "900": {
          "value": "#713307",
          "type": "color",
          "description": "713307"
        }
      },
      "Yellow": {
        "25": {
          "value": "#fefcf6",
          "type": "color",
          "description": "FEFCF6"
        },
        "50": {
          "value": "#fcf2d2",
          "type": "color",
          "description": "FCF2D2"
        },
        "100": {
          "value": "#faebbc",
          "type": "color",
          "description": "FAEBBC"
        },
        "200": {
          "value": "#f8e4a5",
          "type": "color",
          "description": "F8E4A5"
        },
        "300": {
          "value": "#f6dd8f",
          "type": "color",
          "description": "F6DD8F"
        },
        "400": {
          "value": "#f2cf62",
          "type": "color",
          "description": "F2CF62"
        },
        "500": {
          "value": "#eab308",
          "type": "color",
          "description": "EAB308"
        },
        "600": {
          "value": "#bb8f06",
          "type": "color",
          "description": "BB8F06"
        },
        "700": {
          "value": "#8c6b05",
          "type": "color",
          "description": "8C6B05"
        },
        "800": {
          "value": "#5e4803",
          "type": "color",
          "description": "5E4803"
        },
        "900": {
          "value": "#463602",
          "type": "color",
          "description": "463602"
        }
      },
      "Lime": {
        "25": {
          "value": "#fcfff7",
          "type": "color",
          "description": "FCFFF7"
        },
        "50": {
          "value": "#edf9dd",
          "type": "color",
          "description": "EDF9DD"
        },
        "100": {
          "value": "#e1f4c7",
          "type": "color",
          "description": "E1F4C7"
        },
        "200": {
          "value": "#d6efb1",
          "type": "color",
          "description": "D5EFB0"
        },
        "300": {
          "value": "#caea9b",
          "type": "color",
          "description": "CAEA9A"
        },
        "400": {
          "value": "#b3e06e",
          "type": "color",
          "description": "B3E06E"
        },
        "500": {
          "value": "#84cc16",
          "type": "color",
          "description": "84CC16"
        },
        "600": {
          "value": "#6aa312",
          "type": "color",
          "description": "6AA312"
        },
        "700": {
          "value": "#4f7a0d",
          "type": "color",
          "description": "4F7A0D"
        },
        "800": {
          "value": "#355209",
          "type": "color",
          "description": "355209"
        },
        "900": {
          "value": "#283d07",
          "type": "color",
          "description": "283D07"
        }
      },
      "Emerald": {
        "25": {
          "value": "#f9fefc",
          "type": "color",
          "description": "F9FEFC"
        },
        "50": {
          "value": "#dcf7ee",
          "type": "color",
          "description": "DCF7EE"
        },
        "100": {
          "value": "#c5f0e2",
          "type": "color",
          "description": "C5F0E2"
        },
        "200": {
          "value": "#afe9d6",
          "type": "color",
          "description": "AEE9D5"
        },
        "300": {
          "value": "#98e2ca",
          "type": "color",
          "description": "98E2CA"
        },
        "400": {
          "value": "#6bd5b1",
          "type": "color",
          "description": "6BD5B1"
        },
        "500": {
          "value": "#10b981",
          "type": "color",
          "description": "10B981"
        },
        "600": {
          "value": "#00875a",
          "type": "color",
          "description": "00875A"
        },
        "700": {
          "value": "#0a6f4d",
          "type": "color",
          "description": "0A6F4D"
        },
        "800": {
          "value": "#064a34",
          "type": "color",
          "description": "064A34"
        },
        "900": {
          "value": "#053727",
          "type": "color",
          "description": "053727"
        }
      },
      "Teal": {
        "25": {
          "value": "#f6fefd",
          "type": "color",
          "description": "F6FEFD"
        },
        "50": {
          "value": "#dff7f4",
          "type": "color",
          "description": "DFF7F4"
        },
        "100": {
          "value": "#c9f0ec",
          "type": "color",
          "description": "C9F0EC"
        },
        "200": {
          "value": "#b2e9e3",
          "type": "color",
          "description": "B2E9E3"
        },
        "300": {
          "value": "#9ce2da",
          "type": "color",
          "description": "9BE2DA"
        },
        "400": {
          "value": "#6ed4c9",
          "type": "color",
          "description": "6ED4C9"
        },
        "500": {
          "value": "#14b8a6",
          "type": "color",
          "description": "14B8A6"
        },
        "600": {
          "value": "#028577",
          "type": "color",
          "description": "028577"
        },
        "700": {
          "value": "#0c6e64",
          "type": "color",
          "description": "0C6E64"
        },
        "800": {
          "value": "#084a42",
          "type": "color",
          "description": "084942"
        },
        "900": {
          "value": "#063732",
          "type": "color",
          "description": "063732"
        }
      },
      "Cyan": {
        "25": {
          "value": "#fafeff",
          "type": "color",
          "description": "FAFEFF"
        },
        "50": {
          "value": "#dcf6fb",
          "type": "color",
          "description": "DCF6FB"
        },
        "100": {
          "value": "#c4eff6",
          "type": "color",
          "description": "C4EFF6"
        },
        "200": {
          "value": "#ade8f2",
          "type": "color",
          "description": "ACE7F2"
        },
        "300": {
          "value": "#95e0ee",
          "type": "color",
          "description": "95E0EE"
        },
        "400": {
          "value": "#65d2e5",
          "type": "color",
          "description": "65D2E5"
        },
        "500": {
          "value": "#06b6d4",
          "type": "color",
          "description": "06B6D4"
        },
        "600": {
          "value": "#0c8199",
          "type": "color",
          "description": "0C8199"
        },
        "700": {
          "value": "#046d7f",
          "type": "color",
          "description": "036D7F"
        },
        "800": {
          "value": "#024955",
          "type": "color",
          "description": "024955"
        },
        "900": {
          "value": "#023740",
          "type": "color",
          "description": "01363F"
        }
      },
      "Sky": {
        "25": {
          "value": "#f7fdff",
          "type": "color",
          "description": "F7FDFF"
        },
        "50": {
          "value": "#dcf2fc",
          "type": "color",
          "description": "DCF2FC"
        },
        "100": {
          "value": "#c5eafa",
          "type": "color",
          "description": "C5EAFA"
        },
        "200": {
          "value": "#aee1f8",
          "type": "color",
          "description": "AEE1F8"
        },
        "300": {
          "value": "#97d9f6",
          "type": "color",
          "description": "97D9F6"
        },
        "400": {
          "value": "#6ac7f1",
          "type": "color",
          "description": "69C7F1"
        },
        "500": {
          "value": "#0ea5e9",
          "type": "color",
          "description": "0EA5E9"
        },
        "600": {
          "value": "#057eb4",
          "type": "color",
          "description": "057EB4"
        },
        "700": {
          "value": "#08638c",
          "type": "color",
          "description": "08638B"
        },
        "800": {
          "value": "#06425d",
          "type": "color",
          "description": "06425D"
        },
        "900": {
          "value": "#043146",
          "type": "color",
          "description": "043146"
        }
      },
      "Indigo": {
        "25": {
          "value": "#fafaff",
          "type": "color",
          "description": "F7F7FF"
        },
        "50": {
          "value": "#eff0fd",
          "type": "color",
          "description": "EFF0FE"
        },
        "100": {
          "value": "#dfe0fc",
          "type": "color",
          "description": "E0E0FC"
        },
        "200": {
          "value": "#d0d1fa",
          "type": "color",
          "description": "D0D1FA"
        },
        "300": {
          "value": "#c0c1f9",
          "type": "color",
          "description": "C0C2F9"
        },
        "400": {
          "value": "#a1a2f6",
          "type": "color",
          "description": "A1A3F6"
        },
        "500": {
          "value": "#6265f0",
          "type": "color",
          "description": "6366F1"
        },
        "600": {
          "value": "#4f52c8",
          "type": "color",
          "description": "5052C9"
        },
        "700": {
          "value": "#3c3e9f",
          "type": "color",
          "description": "3D3EA1"
        },
        "800": {
          "value": "#2a2b77",
          "type": "color",
          "description": "2A2B79"
        },
        "900": {
          "value": "#202163",
          "type": "color",
          "description": "202165"
        }
      },
      "Violet": {
        "25": {
          "value": "#faf9fe",
          "type": "color",
          "description": "FAF9FE"
        },
        "50": {
          "value": "#f3eefe",
          "type": "color",
          "description": "F3EEFE"
        },
        "100": {
          "value": "#e7ddfc",
          "type": "color",
          "description": "E7DDFC"
        },
        "200": {
          "value": "#dbcdfb",
          "type": "color",
          "description": "DACCFA"
        },
        "300": {
          "value": "#cfbcf9",
          "type": "color",
          "description": "CFBCF9"
        },
        "400": {
          "value": "#b69af7",
          "type": "color",
          "description": "B69AF7"
        },
        "500": {
          "value": "#8657f1",
          "type": "color",
          "description": "8657F1"
        },
        "600": {
          "value": "#6d46c7",
          "type": "color",
          "description": "6D46C7"
        },
        "700": {
          "value": "#55359d",
          "type": "color",
          "description": "55359D"
        },
        "800": {
          "value": "#3c2472",
          "type": "color",
          "description": "3C2472"
        },
        "900": {
          "value": "#301b5d",
          "type": "color",
          "description": "301B5D"
        }
      },
      "Purple": {
        "25": {
          "value": "#fcf9fe",
          "type": "color",
          "description": "FCF9FE"
        },
        "50": {
          "value": "#f5edfd",
          "type": "color",
          "description": "F5EDFD"
        },
        "100": {
          "value": "#ebdbfb",
          "type": "color",
          "description": "EBDBFB"
        },
        "200": {
          "value": "#e1c9f9",
          "type": "color",
          "description": "E1C9F9"
        },
        "300": {
          "value": "#d8b7f7",
          "type": "color",
          "description": "D8B7F7"
        },
        "400": {
          "value": "#c492f4",
          "type": "color",
          "description": "C492F4"
        },
        "500": {
          "value": "#9d4aec",
          "type": "color",
          "description": "9D4AEC"
        },
        "600": {
          "value": "#7f3bbf",
          "type": "color",
          "description": "7F3BBF"
        },
        "700": {
          "value": "#612d93",
          "type": "color",
          "description": "612C92"
        },
        "800": {
          "value": "#431e66",
          "type": "color",
          "description": "431E66"
        },
        "900": {
          "value": "#341750",
          "type": "color",
          "description": "34164F"
        }
      },
      "Fuchsia": {
        "25": {
          "value": "#fdf8fe",
          "type": "color",
          "description": "FDF8FE"
        },
        "50": {
          "value": "#fbecfd",
          "type": "color",
          "description": "FBECFD"
        },
        "100": {
          "value": "#f7dafc",
          "type": "color",
          "description": "F7DAFC"
        },
        "200": {
          "value": "#f4c7fa",
          "type": "color",
          "description": "F4C7FA"
        },
        "300": {
          "value": "#f0b5f9",
          "type": "color",
          "description": "F0B5F9"
        },
        "400": {
          "value": "#e890f5",
          "type": "color",
          "description": "E890F5"
        },
        "500": {
          "value": "#c12ed7",
          "type": "color",
          "description": "C12ED7"
        },
        "600": {
          "value": "#b038c1",
          "type": "color",
          "description": "B038C1"
        },
        "700": {
          "value": "#872a94",
          "type": "color",
          "description": "872A94"
        },
        "800": {
          "value": "#5d1d67",
          "type": "color",
          "description": "5D1C66"
        },
        "900": {
          "value": "#491650",
          "type": "color",
          "description": "481550"
        }
      },
      "Pink": {
        "Pink-500": {
          "value": "#d63283",
          "type": "color",
          "description": "D63283"
        },
        "Pink-25": {
          "value": "#fef8fb",
          "type": "color",
          "description": "FEF8FB"
        },
        "Pink-50": {
          "value": "#fbeaf3",
          "type": "color",
          "description": "FBEAF3"
        },
        "Pink-100": {
          "value": "#f7d6e6",
          "type": "color",
          "description": "F7D6E6"
        },
        "Pink-200": {
          "value": "#f3c1da",
          "type": "color",
          "description": "F3C1DA"
        },
        "Pink-300": {
          "value": "#efadcd",
          "type": "color",
          "description": "EFADCD"
        },
        "Pink-400": {
          "value": "#e684b5",
          "type": "color",
          "description": "E684B5"
        },
        "Pink-600": {
          "value": "#ab2869",
          "type": "color",
          "description": "AB2868"
        },
        "Pink-700": {
          "value": "#801e4f",
          "type": "color",
          "description": "801E4E"
        },
        "Pink-800": {
          "value": "#561434",
          "type": "color",
          "description": "561434"
        },
        "Pink-900": {
          "value": "#400f27",
          "type": "color",
          "description": "400F27"
        }
      },
      "Rose": {
        "25": {
          "value": "#fef9fa",
          "type": "color",
          "description": "FEF9FA"
        },
        "50": {
          "value": "#fbe1e5",
          "type": "color",
          "description": "FBE1E5"
        },
        "100": {
          "value": "#f8cdd4",
          "type": "color",
          "description": "F8CDD4"
        },
        "200": {
          "value": "#f5b9c3",
          "type": "color",
          "description": "F5B9C3"
        },
        "300": {
          "value": "#f2a4b2",
          "type": "color",
          "description": "F2A4B2"
        },
        "400": {
          "value": "#ed7c8f",
          "type": "color",
          "description": "ED7C8F"
        },
        "500": {
          "value": "#e12c4b",
          "type": "color",
          "description": "E12C4B"
        },
        "600": {
          "value": "#bb243e",
          "type": "color",
          "description": "BB243E"
        },
        "700": {
          "value": "#951c31",
          "type": "color",
          "description": "951C31"
        },
        "800": {
          "value": "#6f1524",
          "type": "color",
          "description": "6F1524"
        },
        "900": {
          "value": "#5c111d",
          "type": "color",
          "description": "5C111D"
        }
      }
    },
    "button": {
      "background": {
        "primary": {
          "value": "{Color.Primary.500}",
          "type": "color",
          "hover": {
            "value": "{Color.Primary.700}",
            "type": "color"
          }
        },
        "secondary": {
          "value": "{Color.Base.White}",
          "type": "color"
        }
      }
    },
    "Button": {
      "Color": {
        "Background": {
          "Primary": {
            "Hover": {
              "value": "{Color.Primary.700}",
              "type": "color",
              "description": "#39479B"
            }
          },
          "Secondary": {
            "Hover": {
              "value": "{Color.Neutral.25}",
              "type": "color"
            }
          },
          "Plain": {
            "value": "{Color.Base.transparent}",
            "type": "color"
          }
        },
        "Border": {
          "Primary": {
            "value": "{Color.Primary.500}",
            "type": "color",
            "Hover": {
              "value": "{Color.Primary.700}",
              "type": "color",
              "description": "#39479B"
            }
          },
          "Secondary": {
            "value": "{Color.Neutral.300}",
            "type": "color",
            "description": "#C5C9D0",
            "Hover": {
              "value": "{Color.Neutral.400}",
              "type": "color"
            }
          },
          "Plain": {
            "value": "{Color.Base.transparent}",
            "type": "color"
          }
        }
      },
      "2XL": {
        "value": {
          "fontFamily": "{Default}",
          "fontWeight": "{Semi Bold}",
          "lineHeight": "{Line.Height.Button-2XL}",
          "fontSize": "{Font.Size.Button-2XL}",
          "letterSpacing": "",
          "paragraphSpacing": "",
          "textCase": "",
          "textDecoration": ""
        },
        "type": "typography"
      },
      "XL": {
        "value": {
          "fontFamily": "{Default}",
          "fontWeight": "{Medium}",
          "lineHeight": "{Line.Height.Button-XL}",
          "fontSize": "{Font.Size.Button-XL}",
          "letterSpacing": "",
          "paragraphSpacing": "",
          "textCase": "",
          "textDecoration": ""
        },
        "type": "typography"
      },
      "L": {
        "value": {
          "fontFamily": "{Default}",
          "fontWeight": "{Medium}",
          "lineHeight": "{Line.Height.Button-L}",
          "fontSize": "{Font.Size.Button-L}",
          "letterSpacing": "",
          "paragraphSpacing": "",
          "textCase": "",
          "textDecoration": ""
        },
        "type": "typography"
      },
      "M": {
        "value": {
          "fontFamily": "{Default}",
          "fontWeight": "{Medium}",
          "lineHeight": "{Line.Height.Button-M}",
          "fontSize": "{Font.Size.Button-M}",
          "letterSpacing": "",
          "paragraphSpacing": "",
          "textCase": "",
          "textDecoration": ""
        },
        "type": "typography"
      },
      "S": {
        "value": {
          "fontFamily": "{Default}",
          "fontWeight": "{Medium}",
          "lineHeight": "{Line.Height.Button-S}",
          "fontSize": "{Font.Size.Button-S}",
          "letterSpacing": "",
          "paragraphSpacing": "",
          "textCase": "",
          "textDecoration": ""
        },
        "type": "typography"
      }
    },
    "Shadow": {
      "XS": {
        "value": {
          "x": "0",
          "y": "1",
          "blur": "2",
          "spread": "0",
          "color": "rgba($Color.Neutral.900, 5%)",
          "type": "dropShadow"
        },
        "type": "boxShadow"
      },
      "S": {
        "value": [
          {
            "color": "rgba($Color.Neutral.900, 6%)",
            "type": "dropShadow",
            "x": "0",
            "y": "1",
            "blur": "2",
            "spread": "0"
          },
          {
            "color": "rgba($Color.Neutral.900, 10%)",
            "type": "dropShadow",
            "x": "0",
            "y": "1",
            "blur": "3",
            "spread": "0"
          }
        ],
        "type": "boxShadow"
      },
      "M": {
        "value": [
          {
            "color": "rgba($Color.Neutral.900, 6%)",
            "type": "dropShadow",
            "x": "0",
            "y": "2",
            "blur": "4",
            "spread": "-2"
          },
          {
            "color": "rgba($Color.Neutral.900, 10%)",
            "type": "dropShadow",
            "x": "0",
            "y": "4",
            "blur": "8",
            "spread": "-2"
          }
        ],
        "type": "boxShadow"
      },
      "L": {
        "value": [
          {
            "color": "rgba($Color.Neutral.900, 3%)",
            "type": "dropShadow",
            "x": "0",
            "y": "4",
            "blur": "6",
            "spread": "-2"
          },
          {
            "color": "rgba($Color.Neutral.900, 8%)",
            "type": "dropShadow",
            "x": "0",
            "y": "12",
            "blur": "16",
            "spread": "-4"
          }
        ],
        "type": "boxShadow"
      },
      "XL": {
        "value": [
          {
            "color": "rgba($Color.Neutral.900, 3%)",
            "type": "dropShadow",
            "x": "0",
            "y": "8",
            "blur": "8",
            "spread": "-4"
          },
          {
            "color": "rgba($Color.Neutral.900, 8%)",
            "type": "dropShadow",
            "x": "0",
            "y": "20",
            "blur": "24",
            "spread": "-4"
          }
        ],
        "type": "boxShadow"
      },
      "2XL": {
        "value": {
          "x": "0",
          "y": "24",
          "blur": "48",
          "spread": "-12",
          "color": "rgba($Color.Neutral.900, 18%)",
          "type": "dropShadow"
        },
        "type": "boxShadow"
      },
      "3XL": {
        "value": {
          "x": "0",
          "y": "32",
          "blur": "64",
          "spread": "-12",
          "color": "rgba($Color.Neutral.900, 14%)",
          "type": "dropShadow"
        },
        "type": "boxShadow"
      }
    },
    "States": {
      "Focused Neutral": {
        "value": [
          {
            "color": "#f2f4f7",
            "type": "dropShadow",
            "x": "0",
            "y": "0",
            "blur": "0",
            "spread": "4"
          },
          {
            "color": "#1018280d",
            "type": "dropShadow",
            "x": "0",
            "y": "1",
            "blur": "2",
            "spread": "0"
          }
        ],
        "type": "boxShadow"
      },
      "Focused Primary": {
        "value": [
          {
            "color": "#d9ddf6",
            "type": "dropShadow",
            "x": "0",
            "y": "0",
            "blur": "0",
            "spread": "4"
          },
          {
            "color": "#1018280d",
            "type": "dropShadow",
            "x": "0",
            "y": "1",
            "blur": "2",
            "spread": "0"
          }
        ],
        "type": "boxShadow"
      }
    },
    "Display": {
      "L": {
        "value": {
          "fontFamily": "{font.family}",
          "fontWeight": "{font.weight.semi-bold}",
          "lineHeight": "{line-height.display-l}",
          "fontSize": "{font.size.display-l}",
          "letterSpacing": "",
          "paragraphSpacing": "",
          "textCase": "",
          "textDecoration": ""
        },
        "type": "typography"
      },
      "M": {
        "value": "{Display.L}",
        "type": "typography"
      }
    },
    "Heading": {
      "2XL": {
        "value": {
          "fontFamily": "$fontFamilies.inter",
          "fontWeight": "$fontWeights.inter-0",
          "lineHeight": "$lineHeights.2",
          "fontSize": "$fontSize.7",
          "letterSpacing": "$letterSpacing.0",
          "paragraphSpacing": "$paragraphSpacing.3",
          "textCase": "$textCase.none",
          "textDecoration": "{Text.Decoration.Underline}"
        },
        "type": "typography"
      },
      "XL": {
        "value": {
          "fontFamily": "$fontFamilies.inter",
          "fontWeight": "$fontWeights.inter-0",
          "lineHeight": "$lineHeights.3",
          "fontSize": "$fontSize.6",
          "letterSpacing": "$letterSpacing.0",
          "paragraphSpacing": "$paragraphSpacing.0",
          "textCase": "$textCase.none",
          "textDecoration": "{Text.Decoration.Underline}"
        },
        "type": "typography"
      },
      "L": {
        "value": {
          "fontFamily": "$fontFamilies.inter",
          "fontWeight": "$fontWeights.inter-0",
          "lineHeight": "$lineHeights.4",
          "fontSize": "$fontSize.5",
          "letterSpacing": "$letterSpacing.1",
          "paragraphSpacing": "$paragraphSpacing.0",
          "textCase": "$textCase.none",
          "textDecoration": "{Text.Decoration.Underline}"
        },
        "type": "typography"
      },
      "M": {
        "value": {
          "fontFamily": "$fontFamilies.inter",
          "fontWeight": "$fontWeights.inter-0",
          "lineHeight": "$lineHeights.5",
          "fontSize": "$fontSize.4",
          "letterSpacing": "$letterSpacing.1",
          "paragraphSpacing": "$paragraphSpacing.0",
          "textCase": "$textCase.none",
          "textDecoration": "{Text.Decoration.Underline}"
        },
        "type": "typography"
      },
      "S": {
        "value": {
          "fontFamily": "$fontFamilies.inter",
          "fontWeight": "$fontWeights.inter-0",
          "lineHeight": "$lineHeights.6",
          "fontSize": "$fontSize.2",
          "letterSpacing": "$letterSpacing.1",
          "paragraphSpacing": "$paragraphSpacing.0",
          "textCase": "$textCase.none",
          "textDecoration": "{Text.Decoration.Underline}"
        },
        "type": "typography"
      },
      "XS": {
        "value": {
          "fontFamily": "$fontFamilies.inter",
          "fontWeight": "$fontWeights.inter-0",
          "lineHeight": "$lineHeights.6",
          "fontSize": "$fontSize.1",
          "letterSpacing": "$letterSpacing.1",
          "paragraphSpacing": "$paragraphSpacing.0",
          "textCase": "$textCase.none",
          "textDecoration": "{Text.Decoration.Underline}"
        },
        "type": "typography"
      }
    },
    "Text XL": {
      "Regular": {
        "value": {
          "fontFamily": "$fontFamilies.inter",
          "fontWeight": "$fontWeights.inter-1",
          "lineHeight": "$lineHeights.4",
          "fontSize": "$fontSize.4",
          "letterSpacing": "$letterSpacing.1",
          "paragraphSpacing": "$paragraphSpacing.4",
          "textCase": "$textCase.none",
          "textDecoration": "{Text.Decoration.Underline}"
        },
        "type": "typography"
      },
      "Medium": {
        "value": {
          "fontFamily": "$fontFamilies.inter",
          "fontWeight": "$fontWeights.inter-2",
          "lineHeight": "$lineHeights.4",
          "fontSize": "$fontSize.4",
          "letterSpacing": "$letterSpacing.1",
          "paragraphSpacing": "$paragraphSpacing.4",
          "textCase": "$textCase.none",
          "textDecoration": "{Text.Decoration.Underline}"
        },
        "type": "typography"
      },
      "Bold": {
        "value": {
          "fontFamily": "$fontFamilies.inter",
          "fontWeight": "$fontWeights.inter-0",
          "lineHeight": "$lineHeights.4",
          "fontSize": "$fontSize.4",
          "letterSpacing": "$letterSpacing.1",
          "paragraphSpacing": "$paragraphSpacing.4",
          "textCase": "$textCase.none",
          "textDecoration": "{Text.Decoration.Underline}"
        },
        "type": "typography"
      }
    },
    "Text L": {
      "Regular": {
        "value": {
          "fontFamily": "$fontFamilies.inter",
          "fontWeight": "$fontWeights.inter-1",
          "lineHeight": "$lineHeights.7",
          "fontSize": "$fontSize.2",
          "letterSpacing": "$letterSpacing.1",
          "paragraphSpacing": "$paragraphSpacing.2",
          "textCase": "$textCase.none",
          "textDecoration": "{Text.Decoration.Underline}"
        },
        "type": "typography"
      },
      "Medium": {
        "value": {
          "fontFamily": "$fontFamilies.inter",
          "fontWeight": "$fontWeights.inter-2",
          "lineHeight": "$lineHeights.7",
          "fontSize": "$fontSize.2",
          "letterSpacing": "$letterSpacing.1",
          "paragraphSpacing": "$paragraphSpacing.2",
          "textCase": "$textCase.none",
          "textDecoration": "{Text.Decoration.Underline}"
        },
        "type": "typography"
      },
      "Bold": {
        "value": {
          "fontFamily": "$fontFamilies.inter",
          "fontWeight": "$fontWeights.inter-0",
          "lineHeight": "$lineHeights.7",
          "fontSize": "$fontSize.2",
          "letterSpacing": "$letterSpacing.1",
          "paragraphSpacing": "$paragraphSpacing.2",
          "textCase": "$textCase.none",
          "textDecoration": "{Text.Decoration.Underline}"
        },
        "type": "typography"
      }
    },
    "Text M": {
      "Regular": {
        "value": {
          "fontFamily": "$fontFamilies.inter",
          "fontWeight": "$fontWeights.inter-1",
          "lineHeight": "$lineHeights.6",
          "fontSize": "$fontSize.1",
          "letterSpacing": "$letterSpacing.1",
          "paragraphSpacing": "$paragraphSpacing.1",
          "textCase": "$textCase.none",
          "textDecoration": "{Text.Decoration.Underline}"
        },
        "type": "typography"
      },
      "Medium": {
        "value": {
          "fontFamily": "$fontFamilies.inter",
          "fontWeight": "$fontWeights.inter-2",
          "lineHeight": "$lineHeights.6",
          "fontSize": "$fontSize.1",
          "letterSpacing": "$letterSpacing.1",
          "paragraphSpacing": "$paragraphSpacing.1",
          "textCase": "$textCase.none",
          "textDecoration": "{Text.Decoration.Underline}"
        },
        "type": "typography"
      },
      "Bold": {
        "value": {
          "fontFamily": "$fontFamilies.inter",
          "fontWeight": "$fontWeights.inter-0",
          "lineHeight": "$lineHeights.6",
          "fontSize": "$fontSize.1",
          "letterSpacing": "$letterSpacing.1",
          "paragraphSpacing": "$paragraphSpacing.1",
          "textCase": "$textCase.none",
          "textDecoration": "{Text.Decoration.Underline}"
        },
        "type": "typography"
      }
    },
    "Text S": {
      "Regular": {
        "value": {
          "fontFamily": "$fontFamilies.inter",
          "fontWeight": "$fontWeights.inter-1",
          "lineHeight": "$lineHeights.8",
          "fontSize": "$fontSize.0",
          "letterSpacing": "$letterSpacing.1",
          "paragraphSpacing": "$paragraphSpacing.1",
          "textCase": "$textCase.none",
          "textDecoration": "{Text.Decoration.Underline}"
        },
        "type": "typography"
      },
      "Medium": {
        "value": {
          "fontFamily": "$fontFamilies.inter",
          "fontWeight": "$fontWeights.inter-2",
          "lineHeight": "$lineHeights.8",
          "fontSize": "$fontSize.0",
          "letterSpacing": "$letterSpacing.1",
          "paragraphSpacing": "$paragraphSpacing.1",
          "textCase": "$textCase.none",
          "textDecoration": "{Text.Decoration.Underline}"
        },
        "type": "typography"
      },
      "Bold": {
        "value": {
          "fontFamily": "$fontFamilies.inter",
          "fontWeight": "$fontWeights.inter-0",
          "lineHeight": "$lineHeights.8",
          "fontSize": "$fontSize.0",
          "letterSpacing": "$letterSpacing.1",
          "paragraphSpacing": "$paragraphSpacing.1",
          "textCase": "$textCase.none",
          "textDecoration": "{Text.Decoration.Underline}"
        },
        "type": "typography"
      }
    },
    "space": {
      "none": {
        "value": "0",
        "type": "spacing"
      },
      "3xs": {
        "value": "0.125rem",
        "type": "spacing"
      },
      "2xs": {
        "value": "0.25rem",
        "type": "spacing"
      },
      "xs": {
        "value": "0.5rem",
        "type": "spacing"
      },
      "s": {
        "value": "0.75rem",
        "type": "spacing"
      },
      "m": {
        "value": "1rem",
        "type": "spacing"
      },
      "l": {
        "value": "1.5rem",
        "type": "spacing"
      },
      "xl": {
        "value": "2rem",
        "type": "spacing"
      },
      "2xl": {
        "value": "2.5rem",
        "type": "spacing"
      },
      "3xl": {
        "value": "3rem",
        "type": "spacing"
      },
      "4xl": {
        "value": "4rem",
        "type": "spacing"
      },
      "5xl": {
        "value": "5rem",
        "type": "spacing"
      }
    },
    "Normal": {
      "value": "Regular",
      "type": "fontWeights",
      "description": "Normal font weight is used for body text and form inputs together with “Text” font family."
    },
    "Medium": {
      "value": "Medium",
      "type": "fontWeights",
      "description": "Medium font weight is used for buttons and sub headings together with “Text” font family."
    },
    "Semi Bold": {
      "value": "Semi Bold",
      "type": "fontWeights",
      "description": "Semi bold font weight is used for headings and strong text only together with “Text” font family."
    },
    "Bold": {
      "value": "Bold",
      "type": "fontWeights",
      "description": "Bold font weight is used for headings and strong text only together with “Text” font family."
    },
    "Default": {
      "value": "Inter",
      "type": "fontFamilies",
      "description": "Text font family uses a font stack that gracefully degrades to default system fonts on different platforms. Should be used for body text and form controls."
    },
    "Letter": {
      "Spacing": {
        "Heading": {
          "value": "-0.01rem",
          "type": "letterSpacing",
          "description": "Gives tiny amount of negative letter spacing for the heading text."
        },
        "Overline": {
          "value": "0.003rem",
          "type": "letterSpacing",
          "description": "Letter spacing for overline text"
        }
      }
    },
    "Underline": {
      "value": "underline",
      "type": "textDecoration"
    },
    "Font": {
      "Size": {
        "Display-L": {
          "value": "4.5rem",
          "type": "fontSizes",
          "description": "Display L font size is for marketing purposes and banners."
        },
        "Display-M": {
          "value": "3.75rem",
          "type": "fontSizes",
          "description": "Display M font size is for marketing purposes and banners."
        },
        "Heading-2XL": {
          "value": "3rem",
          "type": "fontSizes",
          "description": "Heading 2XL font size is used for the main heading on desktop."
        },
        "Heading-XL": {
          "value": "2rem",
          "type": "fontSizes",
          "description": "Heading XL font size is used for the main heading on tablet size."
        },
        "Heading-L": {
          "value": "1.5rem",
          "type": "fontSizes",
          "description": "Heading L font size is used for large sub-headings."
        },
        "Heading-M": {
          "value": "1.25rem",
          "type": "fontSizes",
          "description": "Heading M font size is used for the body text."
        },
        "Heading-S": {
          "value": "1rem",
          "type": "fontSizes"
        },
        "Heading-XS": {
          "value": "0.875rem",
          "type": "fontSizes"
        },
        "Text-XL": {
          "value": "1.25rem",
          "type": "fontSizes",
          "description": "Text XL font size is used for small sub-headings."
        },
        "Text-L": {
          "value": "1rem",
          "type": "fontSizes",
          "description": "Text L font size is used for the body text."
        },
        "Text-M": {
          "value": "0.875rem",
          "type": "fontSizes",
          "description": "Text M font size is used for the body text."
        },
        "Text-S": {
          "value": "0.75rem",
          "type": "fontSizes",
          "description": "Text S is used for small text and caption."
        },
        "Overline": {
          "value": "0.685rem",
          "type": "fontSizes",
          "description": "Overline text is used for eyebrow."
        },
        "Button-2XL": {
          "value": "1.125rem",
          "type": "fontSizes",
          "description": "Button 2XL font size."
        },
        "Button-XL": {
          "value": "1rem",
          "type": "fontSizes",
          "description": "Button XL font size."
        },
        "Button-L": {
          "value": "0.875rem",
          "type": "fontSizes",
          "description": "Button L font size."
        },
        "Button-M": {
          "value": "0.875rem",
          "type": "fontSizes",
          "description": "Button M font size."
        },
        "Button-S": {
          "value": "0.75rem",
          "type": "fontSizes",
          "description": "Button S font size."
        }
      }
    },
    "Uppercase": {
      "value": "uppercase",
      "type": "textCase"
    },
    "Line": {
      "Height": {
        "Tight": {
          "value": "1.15em",
          "type": "lineHeights",
          "description": "This token can be used when you don’t want line height taking any extra space."
        },
        "Heading": {
          "value": "1.2em",
          "type": "lineHeights",
          "description": "This is the default line height for headings."
        },
        "Caption": {
          "value": "1.3",
          "type": "lineHeights",
          "description": "This is the default line height for captions, hint texts and form errors."
        },
        "Default": {
          "value": "1.5",
          "type": "lineHeights",
          "description": "Default line-height is used for the main body text. Basically everything else except the headings and sidebar (and a few other exceptions)."
        },
        "Button-2XL": {
          "value": "3.75rem",
          "type": "lineHeights",
          "description": "Button 2XL line height."
        },
        "Button-XL": {
          "value": "3rem",
          "type": "lineHeights",
          "description": "Button XL line height."
        },
        "Button-L": {
          "value": "2.5rem",
          "type": "lineHeights",
          "description": "Button L line height."
        },
        "Button-M": {
          "value": "2.25rem",
          "type": "lineHeights",
          "description": "Button M line height."
        },
        "Button-S": {
          "value": "1.75rem",
          "type": "lineHeights",
          "description": "Button S line height."
        }
      }
    },
    "Border": {
      "Radius": {
        "Circle": {
          "value": "50%",
          "type": "borderRadius",
          "description": "Circle border-radius is used as icon background shape and as avatar shape."
        },
        "Pill": {
          "value": "2em",
          "type": "borderRadius",
          "description": "This is for creating pill shaped tags and similar."
        },
        "Sharp": {
          "value": "0.02em",
          "type": "borderRadius",
          "description": "Sharp border-radius resets the corners to be sharp with no rounding."
        },
        "XS": {
          "value": "0.125rem",
          "type": "borderRadius",
          "description": "This is extra small border radius."
        },
        "S": {
          "value": "0.25rem",
          "type": "borderRadius",
          "description": "This is small border radius."
        },
        "M": {
          "value": "0.5rem",
          "type": "borderRadius",
          "description": "This is the default border Radius."
        },
        "L": {
          "value": "0.75rem",
          "type": "borderRadius",
          "description": "This is large border radius."
        },
        "XL": {
          "value": "1rem",
          "type": "borderRadius",
          "description": "This is extra large border radius."
        }
      }
    }
  },
  "$themes": []
}